pwhl_scraper/__init__.py
pwhl_scraper/cli.py
pwhl_scraper/config.py
pwhl_scraper/py.typed
pwhl_scraper-0.1.0.dist-info/licenses/LICENSE
pwhl_scraper-0.1.0.dist-info/METADATA
pwhl_scraper-0.1.0.dist-info/WHEEL
pwhl_scraper-0.1.0.dist-info/entry_points.txt
pwhl_scraper-0.1.0.dist-info/top_level.txt
pwhl_scraper-0.1.0.dist-info/RECORD
