Metadata-Version: 2.4
Name: pwhl-scraper
Version: 0.1.0
Summary: Data scraper and API for PWHL (Professional Women's Hockey League) statistics
Author-email: Isabelle Lefebvre <ilefe071@gmail.com>
License: MIT
Project-URL: Homepage, https://github.com/IsabelleLefebvre97/pwhl-scraper
Project-URL: Source, https://github.com/IsabelleLefebvre97/pwhl-scraper
Project-URL: Bug Tracker, https://github.com/IsabelleLefebvre97/pwhl-scraper/issues
Classifier: Development Status :: 3 - Alpha
Classifier: Intended Audience :: Developers
Classifier: Intended Audience :: Science/Research
Classifier: License :: OSI Approved :: MIT License
Classifier: Programming Language :: Python :: 3
Classifier: Programming Language :: Python :: 3.7
Classifier: Programming Language :: Python :: 3.8
Classifier: Programming Language :: Python :: 3.9
Classifier: Programming Language :: Python :: 3.10
Classifier: Topic :: Software Development :: Libraries :: Python Modules
Requires-Python: >=3.7
License-File: LICENSE
Requires-Dist: requests>=2.25.0
Requires-Dist: pandas>=1.2.0
Requires-Dist: sqlalchemy>=1.4.0
Requires-Dist: python-dotenv>=0.15.0
Requires-Dist: click>=8.0.0
Requires-Dist: tqdm>=4.60.0
Requires-Dist: numpy>=1.20.0
Requires-Dist: matplotlib>=3.4.0
Requires-Dist: seaborn>=0.11.0
Requires-Dist: tabulate>=0.8.9
Requires-Dist: scipy>=1.8.0
Dynamic: license-file
